easy_viossa_bench/__init__.py
easy_viossa_bench/easy_viossa_bench.py
easy_viossa_bench-0.1.4.dist-info/licenses/LICENSE
easy_viossa_bench-0.1.4.dist-info/METADATA
easy_viossa_bench-0.1.4.dist-info/WHEEL
easy_viossa_bench-0.1.4.dist-info/top_level.txt
easy_viossa_bench-0.1.4.dist-info/RECORD
