Metadata-Version: 2.4
Name: easy_viossa_bench
Version: 0.1.4
Summary: Easily evaluate your model on ViossaBench (viossabench.barnii77.dev)
Author-email: David Harrer <barni@barnii77.dev>
License: MIT License.
Project-URL: Homepage, https://viossabench.barnii77.dev
Classifier: Programming Language :: Python :: 3
Classifier: License :: OSI Approved :: MIT License
Classifier: Operating System :: OS Independent
Requires-Python: >=3.7
License-File: LICENSE
Requires-Dist: requests>=2.31
Dynamic: license-file
